COPYING
COPYING.LESSER
README.md
pyproject.toml
src/dolfinx_external_operator/__init__.py
src/dolfinx_external_operator/external_operator.py
src/dolfinx_external_operator/fem.py
src/dolfinx_external_operator.egg-info/PKG-INFO
src/dolfinx_external_operator.egg-info/SOURCES.txt
src/dolfinx_external_operator.egg-info/dependency_links.txt
src/dolfinx_external_operator.egg-info/requires.txt
src/dolfinx_external_operator.egg-info/top_level.txt
src/dolfinx_external_operator/petsc/__init__.py
src/dolfinx_external_operator/petsc/petsc.py
test/test_codim_external_operator.py
test/test_external_evaluation.py
test/test_external_operators.py
test/test_multiaction.py