Metadata-Version: 2.4
Name: dolfinx-external-operator
Version: 0.10.0
Summary: An implementation of ufl.ExternalOperator for DOLFINx
Author-email: Andrey Latyshev <andrey.latyshev@uni.lu>, "Jack S. Hale" <jack.hale@uni.lu>
License-File: COPYING
License-File: COPYING.LESSER
Requires-Dist: fenics-dolfinx<0.11.0,>=0.10.0
Requires-Dist: fenics-ufl<2026.2.0,>=2025.2.0
Provides-Extra: doc
Requires-Dist: jupyter-book<2.0; extra == "doc"
Requires-Dist: jupytext; extra == "doc"
Provides-Extra: demo
Requires-Dist: gmsh; extra == "demo"
Requires-Dist: numba; extra == "demo"
Requires-Dist: jax[cpu]; extra == "demo"
Requires-Dist: pyvista; extra == "demo"
Requires-Dist: mpltools; extra == "demo"
Provides-Extra: test
Requires-Dist: pytest; extra == "test"
Provides-Extra: lint
Requires-Dist: ruff; extra == "lint"
Provides-Extra: ci
Requires-Dist: dolfinx-external-operator[doc]; extra == "ci"
Requires-Dist: dolfinx-external-operator[demo]; extra == "ci"
Requires-Dist: dolfinx-external-operator[test]; extra == "ci"
Requires-Dist: dolfinx-external-operator[lint]; extra == "ci"
Dynamic: license-file
